i7_hot_reload/__init__.py
i7_hot_reload/hot_reload.py
i7_hot_reload-1.0.0.dist-info/METADATA
i7_hot_reload-1.0.0.dist-info/WHEEL
i7_hot_reload-1.0.0.dist-info/licenses/LICENSE
i7_hot_reload-1.0.0.dist-info/RECORD
