Metadata-Version: 2.4
Name: i7_hot_reload
Version: 1.0.0
Summary: Import or reload a Python module from the CWD
Project-URL: Homepage, https://github.com/imahdimir/i7_hot_reload
Author-email: Mahdi Mir <imahdimir@gmail.com>
License: MIT License
License-File: LICENSE
Keywords: hot_reload
